whisker_autonomic_analysis
