Metadata-Version: 1.1
Name: whisker-autonomic-analysis
Version: 0.3.1
Summary: Analysis of telemetry data for Whisker tasks
Home-page: http://www.whiskercontrol.com/
Author: Rudolf Cardinal
Author-email: rudolf@pobox.com
License: GNU General Public License v3 or later (GPLv3+)
Keywords: autonomic cardinal whisker
Platform: UNKNOWN
Classifier: Development Status :: 3 - Alpha
Classifier: Intended Audience :: Developers
Classifier: License :: OSI Approved :: GNU General Public License v3 or later (GPLv3+)
Classifier: Natural Language :: English
Classifier: Operating System :: OS Independent
Classifier: Programming Language :: Python :: 3
Classifier: Programming Language :: Python :: 3.4
Classifier: Programming Language :: Python :: 3.5
Classifier: Topic :: Software Development :: Libraries
